{
  "$schema": "https://developer.microsoft.com/json-schemas/fabric/item/report/definition/visualContainer/2.0.0/schema.json",
  "name": "0d1d9337a7394e9473e6",
  "position": {
    "x": 430,
    "y": 110,
    "z": 1000,
    "height": 200,
    "width": 410,
    "tabOrder": 1000
  },
  "visual": {
    "visualType": "areaChart",
    "query": {
      "queryState": {
        "Category": {
          "projections": [
            {
              "field": {
                "Column": {
                  "Expression": {
                    "SourceRef": {
                      "Entity": "Calendario"
                    }
                  },
                  "Property": "Date"
                }
              },
              "queryRef": "Calendario.Date",
              "nativeQueryRef": "Date",
              "active": true
            }
          ]
        },
        "Y": {
          "projections": [
            {
              "field": {
                "Measure": {
                  "Expression": {
                    "SourceRef": {
                      "Entity": "Medidas Saldo"
                    }
                  },
                  "Property": "Beneficio Acumulado"
                }
              },
              "queryRef": "Medidas Saldo.Beneficio Acumulado",
              "nativeQueryRef": "Beneficio Acumulado1"
            }
          ]
        }
      },
      "sortDefinition": {
        "sort": [
          {
            "field": {
              "Column": {
                "Expression": {
                  "SourceRef": {
                    "Entity": "Calendario"
                  }
                },
                "Property": "Date"
              }
            },
            "direction": "Ascending"
          }
        ],
        "isDefaultSort": true
      }
    },
    "objects": {
      "labels": [
        {
          "properties": {
            "show": {
              "expr": {
                "Literal": {
                  "Value": "false"
                }
              }
            },
            "labelPosition": {
              "expr": {
                "Literal": {
                  "Value": "'Auto'"
                }
              }
            },
            "labelDensity": {
              "expr": {
                "Literal": {
                  "Value": "28L"
                }
              }
            },
            "color": {
              "solid": {
                "color": {
                  "expr": {
                    "ThemeDataColor": {
                      "ColorId": 8,
                      "Percent": -0.5
                    }
                  }
                }
              }
            }
          }
        },
        {
          "properties": {
            "showSeries": {
              "expr": {
                "Literal": {
                  "Value": "false"
                }
              }
            }
          },
          "selector": {
            "metadata": "Sum(Movimientos.IMPORTE (€))"
          }
        },
        {
          "properties": {
            "showSeries": {
              "expr": {
                "Literal": {
                  "Value": "false"
                }
              }
            }
          },
          "selector": {
            "metadata": "Saldo.Beneficio Inversión Mensual"
          }
        },
        {
          "properties": {
            "showSeries": {
              "expr": {
                "Literal": {
                  "Value": "false"
                }
              }
            }
          },
          "selector": {
            "metadata": "Medidas Saldo.Gastos no Computados"
          }
        },
        {
          "properties": {
            "showSeries": {
              "expr": {
                "Literal": {
                  "Value": "false"
                }
              }
            }
          },
          "selector": {
            "metadata": "Saldo.MoM% de Saldo Actual"
          }
        },
        {
          "properties": {
            "color": {
              "solid": {
                "color": {
                  "expr": {
                    "ThemeDataColor": {
                      "ColorId": 8,
                      "Percent": -0.5
                    }
                  }
                }
              }
            }
          },
          "selector": {
            "data": [
              {
                "dataViewWildcard": {
                  "matchingOption": 1
                }
              }
            ]
          }
        }
      ],
      "categoryAxis": [
        {
          "properties": {
            "preferredCategoryWidth": {
              "expr": {
                "Literal": {
                  "Value": "20D"
                }
              }
            },
            "maxMarginFactor": {
              "expr": {
                "Literal": {
                  "Value": "15L"
                }
              }
            },
            "labelColor": {
              "solid": {
                "color": {
                  "expr": {
                    "ThemeDataColor": {
                      "ColorId": 8,
                      "Percent": -0.5
                    }
                  }
                }
              }
            },
            "showAxisTitle": {
              "expr": {
                "Literal": {
                  "Value": "false"
                }
              }
            }
          }
        }
      ],
      "legend": [
        {
          "properties": {
            "fontSize": {
              "expr": {
                "Literal": {
                  "Value": "8D"
                }
              }
            },
            "labelColor": {
              "solid": {
                "color": {
                  "expr": {
                    "ThemeDataColor": {
                      "ColorId": 8,
                      "Percent": -0.5
                    }
                  }
                }
              }
            }
          }
        }
      ],
      "dataPoint": [
        {
          "properties": {
            "fill": {
              "solid": {
                "color": {
                  "expr": {
                    "ThemeDataColor": {
                      "ColorId": 8,
                      "Percent": 0.4
                    }
                  }
                }
              }
            }
          },
          "selector": {
            "data": [
              {
                "scopeId": {
                  "Comparison": {
                    "ComparisonKind": 0,
                    "Left": {
                      "Column": {
                        "Expression": {
                          "SourceRef": {
                            "Entity": "Tipo Movimiento"
                          }
                        },
                        "Property": "CLASIFICACIÓN"
                      }
                    },
                    "Right": {
                      "Literal": {
                        "Value": "'Colegio'"
                      }
                    }
                  }
                }
              }
            ]
          }
        },
        {
          "properties": {
            "fill": {
              "solid": {
                "color": {
                  "expr": {
                    "ThemeDataColor": {
                      "ColorId": 8,
                      "Percent": 0.2
                    }
                  }
                }
              }
            }
          },
          "selector": {
            "data": [
              {
                "scopeId": {
                  "Comparison": {
                    "ComparisonKind": 0,
                    "Left": {
                      "Column": {
                        "Expression": {
                          "SourceRef": {
                            "Entity": "Tipo Movimiento"
                          }
                        },
                        "Property": "CLASIFICACIÓN"
                      }
                    },
                    "Right": {
                      "Literal": {
                        "Value": "'Luz'"
                      }
                    }
                  }
                }
              }
            ]
          }
        },
        {
          "properties": {
            "fill": {
              "solid": {
                "color": {
                  "expr": {
                    "ThemeDataColor": {
                      "ColorId": 8,
                      "Percent": 0.2
                    }
                  }
                }
              }
            }
          },
          "selector": {
            "metadata": "Saldo.Saldo Actual"
          }
        },
        {
          "properties": {
            "fill": {
              "solid": {
                "color": {
                  "expr": {
                    "ThemeDataColor": {
                      "ColorId": 8,
                      "Percent": -0.5
                    }
                  }
                }
              }
            }
          },
          "selector": {
            "metadata": "Saldo.Saldo Inversiones"
          }
        },
        {
          "properties": {
            "fill": {
              "solid": {
                "color": {
                  "expr": {
                    "ThemeDataColor": {
                      "ColorId": 8,
                      "Percent": -0.25
                    }
                  }
                }
              }
            }
          },
          "selector": {
            "metadata": "Medidas Saldo.Saldo Último"
          }
        },
        {
          "properties": {
            "fill": {
              "solid": {
                "color": {
                  "expr": {
                    "ThemeDataColor": {
                      "ColorId": 8,
                      "Percent": -0.25
                    }
                  }
                }
              }
            }
          }
        },
        {
          "properties": {
            "fill": {
              "solid": {
                "color": {
                  "expr": {
                    "ThemeDataColor": {
                      "ColorId": 8,
                      "Percent": -0.25
                    }
                  }
                }
              }
            }
          },
          "selector": {
            "metadata": "Medidas Saldo.Beneficio Hasta Fecha"
          }
        },
        {
          "properties": {
            "fill": {
              "solid": {
                "color": {
                  "expr": {
                    "ThemeDataColor": {
                      "ColorId": 8,
                      "Percent": -0.25
                    }
                  }
                }
              }
            }
          },
          "selector": {
            "metadata": "Medidas Saldo.Beneficio Acumulado"
          }
        }
      ],
      "valueAxis": [
        {
          "properties": {
            "labelColor": {
              "solid": {
                "color": {
                  "expr": {
                    "ThemeDataColor": {
                      "ColorId": 8,
                      "Percent": -0.5
                    }
                  }
                }
              }
            },
            "labelDisplayUnits": {
              "expr": {
                "Literal": {
                  "Value": "1000D"
                }
              }
            },
            "showAxisTitle": {
              "expr": {
                "Literal": {
                  "Value": "false"
                }
              }
            }
          }
        }
      ],
      "zoom": [
        {
          "properties": {
            "show": {
              "expr": {
                "Literal": {
                  "Value": "false"
                }
              }
            }
          }
        }
      ],
      "trend": [
        {
          "properties": {
            "show": {
              "expr": {
                "Literal": {
                  "Value": "true"
                }
              }
            },
            "displayName": {
              "expr": {
                "Literal": {
                  "Value": "'Línea de tendencia 1'"
                }
              }
            },
            "lineColor": {
              "solid": {
                "color": {
                  "expr": {
                    "ThemeDataColor": {
                      "ColorId": 5,
                      "Percent": -0.25
                    }
                  }
                }
              }
            }
          }
        }
      ],
      "lineStyles": [
        {
          "properties": {
            "strokeWidth": {
              "expr": {
                "Literal": {
                  "Value": "1D"
                }
              }
            },
            "lineChartType": {
              "expr": {
                "Literal": {
                  "Value": "'smooth'"
                }
              }
            },
            "areaMatchStrokeColor": {
              "expr": {
                "Literal": {
                  "Value": "true"
                }
              }
            }
          }
        }
      ]
    },
    "visualContainerObjects": {
      "title": [
        {
          "properties": {
            "text": {
              "expr": {
                "Literal": {
                  "Value": "'Beneficio'"
                }
              }
            },
            "titleWrap": {
              "expr": {
                "Literal": {
                  "Value": "true"
                }
              }
            },
            "fontColor": {
              "solid": {
                "color": {
                  "expr": {
                    "ThemeDataColor": {
                      "ColorId": 8,
                      "Percent": -0.5
                    }
                  }
                }
              }
            }
          }
        }
      ],
      "background": [
        {
          "properties": {
            "show": {
              "expr": {
                "Literal": {
                  "Value": "true"
                }
              }
            },
            "color": {
              "solid": {
                "color": {
                  "expr": {
                    "ThemeDataColor": {
                      "ColorId": 0,
                      "Percent": 0
                    }
                  }
                }
              }
            },
            "transparency": {
              "expr": {
                "Literal": {
                  "Value": "15D"
                }
              }
            }
          }
        }
      ],
      "border": [
        {
          "properties": {
            "show": {
              "expr": {
                "Literal": {
                  "Value": "true"
                }
              }
            },
            "color": {
              "solid": {
                "color": {
                  "expr": {
                    "ThemeDataColor": {
                      "ColorId": 8,
                      "Percent": 0.2
                    }
                  }
                }
              }
            },
            "radius": {
              "expr": {
                "Literal": {
                  "Value": "12D"
                }
              }
            },
            "width": {
              "expr": {
                "Literal": {
                  "Value": "1D"
                }
              }
            }
          }
        }
      ],
      "visualHeader": [
        {
          "properties": {
            "background": {
              "solid": {
                "color": {
                  "expr": {
                    "Literal": {
                      "Value": "'#3a3a3a'"
                    }
                  }
                }
              }
            },
            "border": {
              "solid": {
                "color": {
                  "expr": {
                    "Literal": {
                      "Value": "'#3a3a3a'"
                    }
                  }
                }
              }
            },
            "foreground": {
              "solid": {
                "color": {
                  "expr": {
                    "Literal": {
                      "Value": "'#FFFFFF'"
                    }
                  }
                }
              }
            }
          }
        }
      ],
      "subTitle": [
        {
          "properties": {
            "show": {
              "expr": {
                "Literal": {
                  "Value": "false"
                }
              }
            },
            "fontColor": {
              "solid": {
                "color": {
                  "expr": {
                    "ThemeDataColor": {
                      "ColorId": 8,
                      "Percent": -0.5
                    }
                  }
                }
              }
            }
          }
        }
      ],
      "dropShadow": [
        {
          "properties": {
            "show": {
              "expr": {
                "Literal": {
                  "Value": "true"
                }
              }
            },
            "preset": {
              "expr": {
                "Literal": {
                  "Value": "'Custom'"
                }
              }
            },
            "position": {
              "expr": {
                "Literal": {
                  "Value": "'Outer'"
                }
              }
            },
            "color": {
              "solid": {
                "color": {
                  "expr": {
                    "ThemeDataColor": {
                      "ColorId": 8,
                      "Percent": -0.5
                    }
                  }
                }
              }
            },
            "shadowSpread": {
              "expr": {
                "Literal": {
                  "Value": "1D"
                }
              }
            },
            "shadowDistance": {
              "expr": {
                "Literal": {
                  "Value": "5D"
                }
              }
            }
          }
        }
      ]
    },
    "drillFilterOtherVisuals": true
  },
  "filterConfig": {
    "filters": [
      {
        "name": "4ffe63b8ed636f5676ef",
        "ordinal": 0,
        "field": {
          "Measure": {
            "Expression": {
              "SourceRef": {
                "Entity": "Medidas Saldo"
              }
            },
            "Property": "Beneficio Hasta Fecha"
          }
        },
        "type": "Advanced",
        "howCreated": "User"
      },
      {
        "name": "8ba7cb132a117d8111c4",
        "ordinal": 1,
        "field": {
          "Column": {
            "Expression": {
              "SourceRef": {
                "Entity": "Calendario"
              }
            },
            "Property": "Date"
          }
        },
        "type": "RelativeDate"
      },
      {
        "name": "4ed689ea7c3a4ec05b6c",
        "ordinal": 2,
        "field": {
          "Column": {
            "Expression": {
              "SourceRef": {
                "Entity": "Calendario"
              }
            },
            "Property": "Mes"
          }
        },
        "type": "Categorical",
        "howCreated": "User"
      },
      {
        "name": "8e797fae3d5616d0455e",
        "ordinal": 3,
        "field": {
          "Aggregation": {
            "Expression": {
              "Column": {
                "Expression": {
                  "SourceRef": {
                    "Entity": "Saldo"
                  }
                },
                "Property": "Beneficio Acumulado"
              }
            },
            "Function": 0
          }
        },
        "type": "Advanced",
        "howCreated": "User"
      },
      {
        "name": "eb22b4d6e326d1ec2190",
        "ordinal": 4,
        "field": {
          "Column": {
            "Expression": {
              "SourceRef": {
                "Entity": "Calendario"
              }
            },
            "Property": "FinDeMes"
          }
        },
        "type": "Categorical",
        "filter": {
          "Version": 2,
          "From": [
            {
              "Name": "c",
              "Entity": "Calendario",
              "Type": 0
            }
          ],
          "Where": [
            {
              "Condition": {
                "In": {
                  "Expressions": [
                    {
                      "Column": {
                        "Expression": {
                          "SourceRef": {
                            "Source": "c"
                          }
                        },
                        "Property": "FinDeMes"
                      }
                    }
                  ],
                  "Values": [
                    [
                      {
                        "Literal": {
                          "Value": "1L"
                        }
                      }
                    ]
                  ]
                }
              }
            }
          ]
        },
        "howCreated": "User"
      }
    ],
    "filterSortOrder": "Custom"
  }
}